{
    "groups": {
        "sharedEncounterDeck": {
            "label": "id:sharedEncounterDeck", 
            "tableLabel": "id:encounter",
            "canHaveAttachments": false,
            "shuffleOnLoad": true,
            "onCardEnter": {
                "currentSide": "B",
                "controller": "shared",
                "inPlay": false,
                "rotation": 0,
                "deckGroupId": "sharedEncounterDeck",
                "discardGroupId": "sharedEncounterDiscard"
            }
        },
        "sharedEncounterDiscard": {
            "label": "id:sharedEncounterDiscard", 
            "tableLabel": "id:discard",
            "canHaveAttachments": false,
            "shuffleOnLoad": false,
            "onCardEnter": {
                "currentSide": "A",
                "controller": "shared",
                "inPlay": false,
                "rotation": 0,
                "deckGroupId": "sharedEncounterDeck",
                "discardGroupId": "sharedEncounterDiscard"
            }
        },
        "sharedQuestDeck": {
            "label": "id:sharedQuestDeck", 
            "tableLabel": "id:sharedQuestDeck",
            "canHaveAttachments": false,
            "shuffleOnLoad": false,
            "onCardEnter": {
                "currentSide": "A",
                "inPlay": false,
                "rotation": 0,
                "controller": "shared",
                "deckGroupId": "sharedQuestDeck",
                "discardGroupId": "sharedQuestDiscard"
            }
        },
        "sharedQuestDiscard": {
            "label": "id:sharedQuestDeck", 
            "tableLabel": "id:sharedQuestDeck",
            "canHaveAttachments": false,
            "shuffleOnLoad": false,
            "onCardEnter": {
                "currentSide": "B",
                "inPlay": false,
                "rotation": 0,
                "controller": "shared",
                "deckGroupId": "sharedQuestDeck",
                "discardGroupId": "sharedQuestDiscard"
            }
        },
        "sharedQuestDeck2": {
            "label": "id:sharedQuestDeck2", 
            "tableLabel": "id:sharedQuestDeck2",
            "canHaveAttachments": false,
            "shuffleOnLoad": false,
            "onCardEnter": {
                "currentSide": "A",
                "inPlay": false,
                "rotation": 0,
                "controller": "shared",
                "deckGroupId": "sharedQuestDeck2",
                "discardGroupId": "sharedQuestDiscard2"
            }
        },
        "sharedQuestDiscard2": {
            "label": "id:sharedQuestDeck2", 
            "tableLabel": "id:sharedQuestDeck2",
            "canHaveAttachments": false,
            "shuffleOnLoad": false,
            "onCardEnter": {
                "currentSide": "B",
                "inPlay": false,
                "rotation": 0,
                "controller": "shared",
                "deckGroupId": "sharedQuestDeck2",
                "discardGroupId": "sharedQuestDiscard2"
            }
        },
        "sharedEncounterDeck2": {
            "label": "id:sharedEncounterDeck2", 
            "tableLabel": "id:sharedEncounterDeck2",
            "canHaveAttachments": false,
            "shuffleOnLoad": true,
            "onCardEnter": {
                "currentSide": "B",
                "controller": "shared",
                "inPlay": false,
                "rotation": 0,
                "deckGroupId": "sharedEncounterDeck2",
                "discardGroupId": "sharedEncounterDiscard2"
            }
        },
        "sharedEncounterDiscard2": {
            "label": "id:sharedEncounterDiscard2", 
            "tableLabel": "id:sharedEncounterDiscard2",
            "canHaveAttachments": false,
            "shuffleOnLoad": false,
            "onCardEnter": {
                "currentSide": "A",
                "controller": "shared",
                "inPlay": false,
                "rotation": 0,
                "deckGroupId": "sharedEncounterDeck2",
                "discardGroupId": "sharedEncounterDiscard2"
            }
        },
        "sharedEncounterDeck3": {
            "label": "id:sharedEncounterDeck3", 
            "tableLabel": "id:sharedEncounterDeck3",
            "canHaveAttachments": false,
            "shuffleOnLoad": true,
            "onCardEnter": {
                "currentSide": "B",
                "controller": "shared",
                "inPlay": false,
                "rotation": 0,
                "deckGroupId": "sharedEncounterDeck3",
                "discardGroupId": "sharedEncounterDiscard3"
            }
        },
        "sharedEncounterDiscard3": {
            "label": "id:sharedEncounterDiscard3", 
            "tableLabel": "id:sharedEncounterDiscard3",
            "canHaveAttachments": false,
            "shuffleOnLoad": false,
            "onCardEnter": {
                "currentSide": "A",
                "controller": "shared",
                "inPlay": false,
                "rotation": 0,
                "deckGroupId": "sharedEncounterDeck3",
                "discardGroupId": "sharedEncounterDiscard3"
            }
        },
        "sharedOther": {
            "label": "id:sharedOther", 
            "tableLabel": "id:sharedOther",
            "canHaveAttachments": false,
            "shuffleOnLoad": false,
            "onCardEnter": {
                "currentSide": "A",
                "controller": "shared",
                "inPlay": false
            }
        },
        "sharedSetAside": {
            "label": "id:sharedSetAside", 
            "tableLabel": "id:sharedSetAside",
            "canHaveAttachments": false,
            "shuffleOnLoad": false,
            "onCardEnter": {
                "currentSide": "A",
                "controller": "shared",
                "inPlay": false
            }
        },
        "sharedVictory": {
            "label": "id:sharedVictory", 
            "tableLabel": "id:sharedVictory",
            "canHaveAttachments": false,
            "shuffleOnLoad": false,
            "onCardEnter": {
                "currentSide": "A",
                "inPlay": false
            }
        },
        "sharedStagingArea": {
            "label": "id:sharedStagingArea", 
            "tableLabel": "id:staging",
            "canHaveAttachments": true,
            "shuffleOnLoad": false,
            "onCardEnter": {
                "currentSide": "A",
                "inPlay": true
            }
        },
        "sharedActiveLocation": {
            "label": "id:sharedActiveLocation", 
            "tableLabel": "id:active",
            "canHaveAttachments": true,
            "shuffleOnLoad": false,
            "onCardEnter": {
                "currentSide": "A",
                "inPlay": true
            }
        },
        "sharedMainQuest": {
            "label": "id:sharedMainQuest", 
            "tableLabel": "id:sharedMainQuest",
            "canHaveAttachments": true,
            "shuffleOnLoad": false,
            "onCardEnter": {
                "currentSide": "A",
                "inPlay": true
            }
        },
        "sharedExtra1": {
            "label": "id:sharedExtra1", 
            "tableLabel": "id:sharedExtra1",
            "canHaveAttachments": true,
            "shuffleOnLoad": false,
            "onCardEnter": {
                "currentSide": "A",
                "inPlay": true
            }
        },
        "sharedExtra2": {
            "label": "id:sharedExtra2", 
            "tableLabel": "id:sharedExtra2",
            "canHaveAttachments": true,
            "shuffleOnLoad": false,
            "onCardEnter": {
                "currentSide": "A",
                "inPlay": true
            }
        },
        "sharedExtra3": {
            "label": "id:sharedExtra3", 
            "tableLabel": "id:sharedExtra3",
            "canHaveAttachments": true,
            "shuffleOnLoad": false,
            "onCardEnter": {
                "currentSide": "A",
                "inPlay": true
            }
        },
        "sharedExtra4": {
            "label": "id:sharedExtra4", 
            "tableLabel": "id:sharedExtra4",
            "canHaveAttachments": true,
            "shuffleOnLoad": false,
            "onCardEnter": {
                "currentSide": "A",
                "inPlay": true
            }
        },
        "player1Hand": {
            "label": "id:player1Hand", 
            "tableLabel": "id:hand",
            "canHaveAttachments": false,
            "shuffleOnLoad": false,
            "onCardEnter": {
                "currentSide": "B",
                "controller": "player1",
                "inPlay": false,
                "rotation": 0,
                "peeking": {"player1": true},
                "deckGroupId": "player1Deck",
                "discardGroupId": "player1Discard"
            }
        },
        "player1Deck": {
            "label": "id:player1Deck", 
            "tableLabel": "id:deck",
            "canHaveAttachments": false,
            "shuffleOnLoad": true,
            "onCardEnter": {
                "currentSide": "B",
                "controller": "player1",
                "inPlay": false,
                "rotation": 0,
                "deckGroupId": "player1Deck",
                "discardGroupId": "player1Discard"
            }
        },
        "player1Discard": {
            "label": "id:player1Discard", 
            "tableLabel": "id:discard",
            "canHaveAttachments": false,
            "shuffleOnLoad": false,
            "onCardEnter": {
                "currentSide": "A",
                "controller": "player1",
                "inPlay": false,
                "rotation": 0,
                "deckGroupId": "player1Deck",
                "discardGroupId": "player1Discard"
            }
        },
        "player1Deck2": {
            "label": "id:player1Deck2", 
            "tableLabel": "id:player1Deck2",
            "canHaveAttachments": false,
            "shuffleOnLoad": true,
            "onCardEnter": {
                "currentSide": "B",
                "controller": "player1",
                "inPlay": false,
                "rotation": 0,
                "deckGroupId": "player1Deck2",
                "discardGroupId": "player1Discard"
            }
        },
        "player1Play1": {
            "label": "id:player1Play1", 
            "tableLabel": "id:playArea",
            "canHaveAttachments": true,
            "shuffleOnLoad": false,
            "onCardEnter": {
                "currentSide": "A",
                "controller": "player1",
                "inPlay": true
            }
        },
        "player1Play2": {
            "label": "id:player1Play2", 
            "tableLabel": "id:playArea",
            "canHaveAttachments": true,
            "shuffleOnLoad": false,
            "onCardEnter": {
                "currentSide": "A",
                "controller": "player1",
                "inPlay": true
            }
        },
        "player1Play3": {
            "label": "id:player1Play3", 
            "tableLabel": "id:playArea",
            "canHaveAttachments": true,
            "shuffleOnLoad": false,
            "onCardEnter": {
                "currentSide": "A",
                "controller": "player1",
                "inPlay": true
            }
        },
        "player1Play4": {
            "label": "id:player1Play4", 
            "tableLabel": "id:playArea",
            "canHaveAttachments": true,
            "shuffleOnLoad": false,
            "onCardEnter": {
                "currentSide": "A",
                "controller": "player1",
                "inPlay": true
            }
        },
        "player1Engaged": {
            "label": "id:player1Engaged", 
            "tableLabel": "id:engaged",
            "canHaveAttachments": true,
            "shuffleOnLoad": false,
            "onCardEnter": {
                "currentSide": "A",
                "controller": "shared",
                "inPlay": true
            }
        },
        "player1Event": {
            "label": "id:player1Event", 
            "tableLabel": "id:event",
            "canHaveAttachments": true,
            "shuffleOnLoad": false,
            "onCardEnter": {
                "currentSide": "A",
                "controller": "player1",
                "inPlay": true
            }
        },
        "player1Sideboard": {
            "label": "id:player1Sideboard", 
            "tableLabel": "id:sideboard",
            "canHaveAttachments": false,
            "shuffleOnLoad": false,
            "onCardEnter": {
                "currentSide": "A",
                "controller": "player1",
                "inPlay": true
            }
        },
        "player2Hand": {
            "label": "id:player2Hand", 
            "tableLabel": "id:hand",
            "canHaveAttachments": false,
            "shuffleOnLoad": false,
            "onCardEnter": {
                "currentSide": "B",
                "controller": "player2",
                "inPlay": false,
                "rotation": 0,
                "peeking": {"player2": true},
                "deckGroupId": "player2Deck",
                "discardGroupId": "player2Discard"
            }
        },
        "player2Deck": {
            "label": "id:player2Deck", 
            "tableLabel": "id:deck",
            "canHaveAttachments": false,
            "shuffleOnLoad": true,
            "onCardEnter": {
                "currentSide": "B",
                "controller": "player2",
                "inPlay": false,
                "rotation": 0,
                "deckGroupId": "player2Deck",
                "discardGroupId": "player2Discard"
            }
        },
        "player2Discard": {
            "label": "id:player2Discard", 
            "tableLabel": "id:discard",
            "canHaveAttachments": false,
            "shuffleOnLoad": false,
            "onCardEnter": {
                "currentSide": "A",
                "controller": "player2",
                "inPlay": false,
                "rotation": 0,
                "deckGroupId": "player2Deck",
                "discardGroupId": "player2Discard"
            }
        },
        "player2Deck2": {
            "label": "id:player2Deck2", 
            "tableLabel": "id:player2Deck2",
            "canHaveAttachments": false,
            "shuffleOnLoad": true,
            "onCardEnter": {
                "currentSide": "B",
                "controller": "player2",
                "inPlay": false,
                "rotation": 0,
                "deckGroupId": "player2Deck2",
                "discardGroupId": "player2Discard"
            }
        },
        "player2Play1": {
            "label": "id:player2Play1", 
            "tableLabel": "id:playArea",
            "canHaveAttachments": true,
            "shuffleOnLoad": false,
            "onCardEnter": {
                "currentSide": "A",
                "controller": "player2",
                "inPlay": true
            }
        },
        "player2Play2": {
            "label": "id:player2Play2", 
            "tableLabel": "id:playArea",
            "canHaveAttachments": true,
            "shuffleOnLoad": false,
            "onCardEnter": {
                "currentSide": "A",
                "controller": "player2",
                "inPlay": true
            }
        },
        "player2Play3": {
            "label": "id:player2Play3", 
            "tableLabel": "id:playArea",
            "canHaveAttachments": true,
            "shuffleOnLoad": false,
            "onCardEnter": {
                "currentSide": "A",
                "controller": "player2",
                "inPlay": true
            }
        },
        "player2Play4": {
            "label": "id:player2Play4", 
            "tableLabel": "id:playArea",
            "canHaveAttachments": true,
            "shuffleOnLoad": false,
            "onCardEnter": {
                "currentSide": "A",
                "controller": "player2",
                "inPlay": true
            }
        },
        "player2Engaged": {
            "label": "id:player2Engaged", 
            "tableLabel": "id:engaged",
            "canHaveAttachments": true,
            "shuffleOnLoad": false,
            "onCardEnter": {
                "currentSide": "A",
                "controller": "shared",
                "inPlay": true
            }
        },
        "player2Event": {
            "label": "id:player2Event", 
            "tableLabel": "id:event",
            "canHaveAttachments": true,
            "shuffleOnLoad": false,
            "onCardEnter": {
                "currentSide": "A",
                "controller": "player2",
                "inPlay": true
            }
        },
        "player2Sideboard": {
            "label": "id:player2Sideboard", 
            "tableLabel": "id:sideboard",
            "canHaveAttachments": false,
            "shuffleOnLoad": false,
            "onCardEnter": {
                "currentSide": "A",
                "controller": "player2",
                "inPlay": true
            }
        },
        "player3Hand": {
            "label": "id:player3Hand", 
            "tableLabel": "id:hand",
            "canHaveAttachments": false,
            "shuffleOnLoad": false,
            "onCardEnter": {
                "currentSide": "B",
                "controller": "player3",
                "inPlay": false,
                "rotation": 0,
                "peeking": {"player3": true},
                "deckGroupId": "player3Deck",
                "discardGroupId": "player3Discard"
            }
        },
        "player3Deck": {
            "label": "id:player3Deck", 
            "tableLabel": "id:deck",
            "canHaveAttachments": false,
            "shuffleOnLoad": true,
            "onCardEnter": {
                "currentSide": "B",
                "controller": "player3",
                "inPlay": false,
                "rotation": 0,
                "deckGroupId": "player3Deck",
                "discardGroupId": "player3Discard"
            }
        },
        "player3Discard": {
            "label": "id:player3Discard", 
            "tableLabel": "id:discard",
            "canHaveAttachments": false,
            "shuffleOnLoad": false,
            "onCardEnter": {
                "currentSide": "A",
                "controller": "player3",
                "inPlay": false,
                "rotation": 0,
                "deckGroupId": "player3Deck",
                "discardGroupId": "player3Discard"
            }
        },
        "player3Deck2": {
            "label": "id:player3Deck2", 
            "tableLabel": "id:player3Deck2",
            "canHaveAttachments": false,
            "shuffleOnLoad": true,
            "onCardEnter": {
                "currentSide": "B",
                "controller": "player3",
                "inPlay": false,
                "rotation": 0,
                "deckGroupId": "player3Deck2",
                "discardGroupId": "player3Discard"
            }
        },
        "player3Play1": {
            "label": "id:player3Play1", 
            "tableLabel": "id:playArea",
            "canHaveAttachments": true,
            "shuffleOnLoad": false,
            "onCardEnter": {
                "currentSide": "A",
                "controller": "player3",
                "inPlay": true
            }
        },
        "player3Play2": {
            "label": "id:player3Play2", 
            "tableLabel": "id:playArea",
            "canHaveAttachments": true,
            "shuffleOnLoad": false,
            "onCardEnter": {
                "currentSide": "A",
                "controller": "player3",
                "inPlay": true
            }
        },
        "player3Play3": {
            "label": "id:player3Play3", 
            "tableLabel": "id:playArea",
            "canHaveAttachments": true,
            "shuffleOnLoad": false,
            "onCardEnter": {
                "currentSide": "A",
                "controller": "player3",
                "inPlay": true
            }
        },
        "player3Play4": {
            "label": "id:player3Play4", 
            "tableLabel": "id:playArea",
            "canHaveAttachments": true,
            "shuffleOnLoad": false,
            "onCardEnter": {
                "currentSide": "A",
                "controller": "player3",
                "inPlay": true
            }
        },
        "player3Engaged": {
            "label": "id:player3Engaged", 
            "tableLabel": "id:engaged",
            "canHaveAttachments": true,
            "shuffleOnLoad": false,
            "onCardEnter": {
                "currentSide": "A",
                "controller": "shared",
                "inPlay": true
            }
        },
        "player3Event": {
            "label": "id:player3Event", 
            "tableLabel": "id:event",
            "canHaveAttachments": true,
            "shuffleOnLoad": false,
            "onCardEnter": {
                "currentSide": "A",
                "controller": "player3",
                "inPlay": true
            }
        },
        "player3Sideboard": {
            "label": "id:player3Sideboard", 
            "tableLabel": "id:sideboard",
            "canHaveAttachments": false,
            "shuffleOnLoad": false,
            "onCardEnter": {
                "currentSide": "A",
                "controller": "player3",
                "inPlay": true
            }
        },
        "player4Hand": {
            "label": "id:player4Hand", 
            "tableLabel": "id:hand",
            "canHaveAttachments": false,
            "shuffleOnLoad": false,
            "onCardEnter": {
                "currentSide": "B",
                "controller": "player4",
                "inPlay": false,
                "rotation": 0,
                "peeking": {"player4": true},
                "deckGroupId": "player4Deck",
                "discardGroupId": "player4Discard"
            }
        },
        "player4Deck": {
            "label": "id:player4Deck", 
            "tableLabel": "id:deck",
            "canHaveAttachments": false,
            "shuffleOnLoad": true,
            "onCardEnter": {
                "currentSide": "B",
                "controller": "player4",
                "inPlay": false,
                "rotation": 0,
                "deckGroupId": "player4Deck",
                "discardGroupId": "player4Discard"
            }
        },
        "player4Discard": {
            "label": "id:player4Discard", 
            "tableLabel": "id:discard",
            "canHaveAttachments": false,
            "shuffleOnLoad": false,
            "onCardEnter": {
                "currentSide": "A",
                "controller": "player4",
                "inPlay": false,
                "rotation": 0,
                "deckGroupId": "player4Deck",
                "discardGroupId": "player4Discard"
            }
        },
        "player4Deck2": {
            "label": "id:player4Deck2", 
            "tableLabel": "id:player4Deck2",
            "canHaveAttachments": false,
            "shuffleOnLoad": true,
            "onCardEnter": {
                "currentSide": "B",
                "controller": "player4",
                "inPlay": false,
                "rotation": 0,
                "deckGroupId": "player4Deck2",
                "discardGroupId": "player4Discard"
            }
        },
        "player4Play1": {
            "label": "id:player4Play1", 
            "tableLabel": "id:playArea",
            "canHaveAttachments": true,
            "shuffleOnLoad": false,
            "onCardEnter": {
                "currentSide": "A",
                "controller": "player4",
                "inPlay": true
            }
        },
        "player4Play2": {
            "label": "id:player4Play2", 
            "tableLabel": "id:playArea",
            "canHaveAttachments": true,
            "shuffleOnLoad": false,
            "onCardEnter": {
                "currentSide": "A",
                "controller": "player4",
                "inPlay": true
            }
        },
        "player4Play3": {
            "label": "id:player4Play3", 
            "tableLabel": "id:playArea",
            "canHaveAttachments": true,
            "shuffleOnLoad": false,
            "onCardEnter": {
                "currentSide": "A",
                "controller": "player4",
                "inPlay": true
            }
        },
        "player4Play4": {
            "label": "id:player4Play4", 
            "tableLabel": "id:playArea",
            "canHaveAttachments": true,
            "shuffleOnLoad": false,
            "onCardEnter": {
                "currentSide": "A",
                "controller": "player4",
                "inPlay": true
            }
        },
        "player4Engaged": {
            "label": "id:player4Engaged", 
            "tableLabel": "id:engaged",
            "canHaveAttachments": true,
            "shuffleOnLoad": false,
            "onCardEnter": {
                "currentSide": "A",
                "controller": "shared",
                "inPlay": true
            }
        },
        "player4Event": {
            "label": "id:player4Event", 
            "tableLabel": "id:event",
            "canHaveAttachments": true,
            "shuffleOnLoad": false,
            "onCardEnter": {
                "currentSide": "A",
                "controller": "player4",
                "inPlay": true
            }
        },
        "player4Sideboard": {
            "label": "id:player4Sideboard", 
            "tableLabel": "id:sideboard",
            "canHaveAttachments": false,
            "shuffleOnLoad": false,
            "onCardEnter": {
                "currentSide": "A",
                "controller": "player4",
                "inPlay": true
            }
        }
    }
}